pyfaces
