Metadata-Version: 1.0
Name: Pyfaces
Version: 0.2.0
Summary: A package to ease face recognition tasks using Dlib
Home-page: https://github.com/febrezo/pyfaces
Author: Félix Brezo (@febrezo)
Author-email: UNKNOWN
License: GNU AGPLv3+
Platform: UNKNOWN
